geo2zip/__init__.py
geo2zip/geo2zip.py
geo2zip/main.py
geo2zip/data/ca.csv
geo2zip/data/us.csv
geo2zip-0.1.6.dist-info/LICENSE
geo2zip-0.1.6.dist-info/METADATA
geo2zip-0.1.6.dist-info/WHEEL
geo2zip-0.1.6.dist-info/entry_points.txt
geo2zip-0.1.6.dist-info/top_level.txt
geo2zip-0.1.6.dist-info/RECORD
