Metadata-Version: 2.1
Name: geo2zip
Version: 0.1.6
Summary: Geo2Zip is a Python package that provides a fast and efficient way to find the closest US ZIP code for a given latitude and longitude. It uses a KDTree for quick nearest-neighbor lookup, making it suitable for geospatial queries.
Home-page: https://github.com/jlopex/geo2zip
Author: Javier Lopez
Author-email: jlopex@gmail.com
License: MIT
Classifier: Programming Language :: Python :: 3
Classifier: License :: OSI Approved :: MIT License
Classifier: Operating System :: OS Independent
Requires-Python: >=3.7
License-File: LICENSE
Requires-Dist: haversine
Requires-Dist: scipy
Provides-Extra: dev
Requires-Dist: pytest; extra == "dev"
